JiyuShenduXuexiDeTuijianXitongYanjiuZongshuHuangliweiDeng/README.md
JiyuShenduXuexiDeTuijianXitongYanjiuZongshuHuangliweiDeng/__init__.py
JiyuShenduXuexiDeTuijianXitongYanjiuZongshuHuangliweiDeng/__main__.py
JiyuShenduXuexiDeTuijianXitongYanjiuZongshuHuangliweiDeng/file.pdf
JiyuShenduXuexiDeTuijianXitongYanjiuZongshuHuangliweiDeng/index.html
jiyu_shendu_xuexi_de_tuijian_xitong_yanjiu_zongshu_huangliwei_deng-2024.3.4.0.dist-info/METADATA
jiyu_shendu_xuexi_de_tuijian_xitong_yanjiu_zongshu_huangliwei_deng-2024.3.4.0.dist-info/WHEEL
jiyu_shendu_xuexi_de_tuijian_xitong_yanjiu_zongshu_huangliwei_deng-2024.3.4.0.dist-info/entry_points.txt
jiyu_shendu_xuexi_de_tuijian_xitong_yanjiu_zongshu_huangliwei_deng-2024.3.4.0.dist-info/top_level.txt
jiyu_shendu_xuexi_de_tuijian_xitong_yanjiu_zongshu_huangliwei_deng-2024.3.4.0.dist-info/RECORD
